<?xml version="1.0"?>
<!--
/**
 * GoMage.com
 *
 * GoMage Feed Pro M2
 *
 * @category     Extension
 * @copyright    Copyright (c) 2010-2018 GoMage.com (https://www.gomage.com)
 * @author       GoMage.com
 * @license      https://www.gomage.com/licensing  Single domain license
 * @terms of use https://www.gomage.com/terms-of-use
 * @version      Release: 1.2.0
 * @since        Class available since Release 1.0.0
 */
-->
<page xmlns:xsi="http://www.w3.org/2001/XMLSchema-instance" xsi:noNamespaceSchemaLocation="urn:magento:framework:View/Layout/etc/page_configuration.xsd">
    <head>
        <css src="GoMage_Feed::css/styles.css"/>
    </head>
    <body>
        <referenceContainer name="content">
            <uiComponent name="gomage_feed_attribute_listing"/>
        </referenceContainer>
    </body>
</page>
